{"chunk_definitions":[{"chunk_id":"cz3djt0xi1szy","chunk_label":"unnamed-chunk-1","document_id":"5B92D629","expansion_state":0,"options":{"echo":false,"engine":"r","label":"unnamed-chunk-2","message":false},"row":14,"row_count":1,"visible":true},{"chunk_id":"cdaxh137y36q2","chunk_label":"unnamed-chunk-2","document_id":"642C7BDD","expansion_state":0,"options":{"engine":"r","label":"unnamed-chunk-3"},"row":26,"row_count":1,"visible":true},{"chunk_id":"cwrycvaswhzix","chunk_label":"unnamed-chunk-3","document_id":"5B92D629","expansion_state":0,"options":{"engine":"r","label":"unnamed-chunk-4"},"row":35,"row_count":1,"visible":true},{"chunk_id":"c69oe8nt7crfy","chunk_label":"unnamed-chunk-4","document_id":"5B92D629","expansion_state":0,"options":{"engine":"r","label":"unnamed-chunk-5"},"row":44,"row_count":1,"visible":true},{"chunk_id":"cifpcxp2msv1i","chunk_label":"unnamed-chunk-5","document_id":"5B92D629","expansion_state":0,"options":{"engine":"r","label":"unnamed-chunk-6"},"row":53,"row_count":1,"visible":true},{"chunk_id":"c5dgtejqdni42","chunk_label":"unnamed-chunk-6","document_id":"5B92D629","expansion_state":0,"options":{"engine":"r","label":"unnamed-chunk-7"},"row":58,"row_count":1,"visible":true},{"chunk_id":"cr22qc3wcvsq5","chunk_label":"unnamed-chunk-7","document_id":"5B92D629","expansion_state":0,"options":{"engine":"r","label":"unnamed-chunk-8"},"row":67,"row_count":1,"visible":true},{"chunk_id":"cadoyeqfn9zdl","chunk_label":"unnamed-chunk-8","document_id":"5B92D629","expansion_state":0,"options":{"engine":"r","label":"unnamed-chunk-10"},"row":78,"row_count":1,"visible":true},{"chunk_id":"cdpxuh9sbv7ca","chunk_label":"unnamed-chunk-9","document_id":"5B92D629","expansion_state":0,"options":{"engine":"r","label":"unnamed-chunk-11"},"row":93,"row_count":1,"visible":true},{"chunk_id":"ct6bkoljizx7l","chunk_label":"unnamed-chunk-10","document_id":"5B92D629","expansion_state":0,"options":{"engine":"r","label":"unnamed-chunk-12"},"row":104,"row_count":1,"visible":true},{"chunk_id":"c4cxjvbjye1j9","chunk_label":"unnamed-chunk-11","document_id":"5B92D629","expansion_state":0,"options":{"engine":"r","label":"unnamed-chunk-13"},"row":113,"row_count":1,"visible":true},{"chunk_id":"cjrjy8qvpztrb","chunk_label":"unnamed-chunk-12","document_id":"5B92D629","expansion_state":0,"options":{"engine":"r","label":"unnamed-chunk-14"},"row":122,"row_count":1,"visible":true},{"chunk_id":"c64z3dc1gefp6","chunk_label":"unnamed-chunk-13","document_id":"5B92D629","expansion_state":0,"options":{"engine":"r","label":"unnamed-chunk-15"},"row":131,"row_count":1,"visible":true},{"chunk_id":"cfrnwk1asr4yq","chunk_label":"unnamed-chunk-14","document_id":"5B92D629","expansion_state":0,"options":{"engine":"r","label":"unnamed-chunk-16"},"row":140,"row_count":1,"visible":true}],"doc_write_time":1556693675}